[
  {
    "id": "ZSaIoxAAADNdr4V6",
    "name": "A Coruña",
    "uid": "a-coruna",
    "keywords": "Spain Europe",
    "lat": 43.362344,
    "lng": -8.41154,
    "bounds": {
      "latitudeStart": 43.337341,
      "longitudeStart": -8.438259,
      "latitudeEnd": 43.386407,
      "longitudeEnd": -8.387108
    }
  },
  {
    "id": "ZSaIXhAAAM1cr4Ql",
    "name": "Accra",
    "uid": "accra",
    "keywords": "Ghana Africa",
    "lat": 5.559285,
    "lng": -0.197431,
    "bounds": {
      "latitudeStart": 5.513987,
      "longitudeStart": -0.29912,
      "latitudeEnd": 5.66843,
      "longitudeEnd": -0.060339
    }
  },
  {
    "id": "ZSaIERAAACVdr4Kt",
    "name": "Adelaide",
    "uid": "adelaide",
    "keywords": "Australia South SA",
    "lat": -34.928499,
    "lng": 138.600746,
    "bounds": {
      "latitudeStart": -35.34897,
      "longitudeStart": 138.44213,
      "latitudeEnd": -34.652564,
      "longitudeEnd": 138.78019
    }
  },
  {
    "id": "ZSaH1xAAAM1cr4Ga",
    "name": "Alaska",
    "uid": "alaska",
    "keywords": "America United States USA",
    "lat": 64.79457321751367,
    "lng": -151.0721290893268,
    "bounds": {
      "latitudeStart": 51.175092,
      "longitudeStart": 172.347846,
      "latitudeEnd": 71.439786,
      "longitudeEnd": -129.974194
    }
  },
  {
    "id": "ZSaHjBAAAO9cr4A7",
    "name": "Alice Springs",
    "uid": "alice-springs",
    "keywords": "Australia NT Northern Territory",
    "lat": -23.698042,
    "lng": 133.880747,
    "bounds": {
      "latitudeStart": -25.999058,
      "longitudeStart": 129.000476,
      "latitudeEnd": -10.965914,
      "longitudeEnd": 138.0012
    }
  },
  {
    "id": "ZSaHNxAAACVdr36d",
    "name": "Amsterdam",
    "uid": "amsterdam",
    "keywords": "Netherlands Europe",
    "lat": 52.367573,
    "lng": 4.904139,
    "bounds": {
      "latitudeStart": 52.278174,
      "longitudeStart": 4.728759,
      "latitudeEnd": 52.431157,
      "longitudeEnd": 5.079162
    }
  },
  {
    "id": "ZSaG8BAAADNdr31L",
    "name": "Auckland",
    "uid": "auckland",
    "keywords": "New Zealand NZ",
    "lat": -36.850883,
    "lng": 174.764488,
    "region": {
      "latitude": -36.850883,
      "longitude": 174.764488,
      "latitudeDelta": 0.05,
      "longitudeDelta": 0.05
    },
    "bounds": {
      "latitudeStart": -37.05902,
      "longitudeStart": 174.443816,
      "latitudeEnd": -36.660602,
      "longitudeEnd": 174.968426
    },
    "trending": true
  },
  {
    "id": "ZSaGrhAAAIFcr3wJ",
    "name": "Austin",
    "uid": "austin",
    "keywords": "America United States USA Texas",
    "lat": 30.267153,
    "lng": -97.743061,
    "bounds": {
      "latitudeStart": 30.098659,
      "longitudeStart": -97.938383,
      "latitudeEnd": 30.516863,
      "longitudeEnd": -97.573102
    }
  },
  {
    "id": "ZSaGXxAAACBdr3tL",
    "name": "Bali",
    "uid": "bali",
    "keywords": "Indonesia Asia",
    "lat": -8.409518,
    "lng": 115.188916,
    "region": {
      "latitude": -8.409518,
      "longitude": 115.188916,
      "latitudeDelta": 0.5,
      "longitudeDelta": 0.5
    },
    "bounds": {
      "latitudeStart": -8.849261,
      "longitudeStart": 114.431626,
      "latitudeEnd": -8.061682,
      "longitudeEnd": 115.711528
    },
    "trending": true
  },
  {
    "id": "ZSaGHxAAAIVcr3pW",
    "name": "Bangalore",
    "uid": "bangalore",
    "keywords": "India Asia",
    "lat": 12.971599,
    "lng": 77.594563,
    "bounds": {
      "latitudeStart": 12.734289,
      "longitudeStart": 77.379198,
      "latitudeEnd": 13.173706,
      "longitudeEnd": 77.882681
    }
  },
  {
    "id": "ZSaFfhAAACVdr3el",
    "name": "Bangkok",
    "uid": "bangkok",
    "keywords": "Thailand Asia",
    "lat": 13.756331,
    "lng": 100.501765,
    "region": {
      "latitude": 13.736151,
      "longitude": 100.513589,
      "latitudeDelta": 0.05,
      "longitudeDelta": 0.05
    },
    "bounds": {
      "latitudeStart": 13.494088,
      "longitudeStart": 100.327814,
      "latitudeEnd": 13.955111,
      "longitudeEnd": 100.938408
    },
    "trending": true
  },
  {
    "id": "ZSaE_RAAAKFcr3VM",
    "name": "Barbados",
    "uid": "barbados",
    "keywords": "Caribbean",
    "lat": 13.193887,
    "lng": -59.543198,
    "bounds": {
      "latitudeStart": 13.039844,
      "longitudeStart": -59.653015,
      "latitudeEnd": 13.336509,
      "longitudeEnd": -59.417496
    }
  },
  {
    "id": "ZSaEhhAAAM1cr3L6",
    "name": "Barcelona",
    "uid": "barcelona",
    "keywords": "Spain Europe",
    "lat": 41.387397,
    "lng": 2.168568,
    "region": {
      "latitude": 41.387397,
      "longitude": 2.168568,
      "latitudeDelta": 0.05,
      "longitudeDelta": 0.05
    },
    "bounds": {
      "latitudeStart": 41.317039,
      "longitudeStart": 2.052333,
      "latitudeEnd": 41.468297,
      "longitudeEnd": 2.228045
    },
    "trending": true
  },
  {
    "id": "ZSaD2xAAADNdr2-1",
    "name": "Beirut",
    "uid": "beirut",
    "keywords": "Lebanon Middle East",
    "lat": 33.893791,
    "lng": 35.501777,
    "bounds": {
      "latitudeStart": 33.862328,
      "longitudeStart": 35.466928,
      "latitudeEnd": 33.916109,
      "longitudeEnd": 35.541636
    }
  },
  {
    "id": "ZSaDYBAAADNdr21K",
    "name": "Berlin",
    "uid": "berlin",
    "keywords": "Germany Europe",
    "lat": 52.520007,
    "lng": 13.404954,
    "region": {
      "latitude": 52.520007,
      "longitude": 13.404954,
      "latitudeDelta": 0.05,
      "longitudeDelta": 0.05
    },
    "bounds": {
      "latitudeStart": 52.338234,
      "longitudeStart": 13.088346,
      "latitudeEnd": 52.675454,
      "longitudeEnd": 13.761118
    },
    "trending": true
  },
  {
    "id": "ZRygOREAADMDjU2V",
    "name": "Bhutan",
    "uid": "bhutan",
    "keywords": "Asia",
    "lat": 27.514162,
    "lng": 90.433601,
    "bounds": {
      "latitudeStart": 26.702021,
      "longitudeStart": 88.745522,
      "latitudeEnd": 28.247806,
      "longitudeEnd": 92.125232
    }
  },
  {
    "id": "ZSaDFBAAACBdr2vn",
    "name": "Biarritz",
    "uid": "biarritz",
    "keywords": "France Europe",
    "lat": 43.483152,
    "lng": -1.558626,
    "bounds": {
      "latitudeStart": 43.447407,
      "longitudeStart": -1.577191,
      "latitudeEnd": 43.494513,
      "longitudeEnd": -1.534389
    }
  },
  {
    "id": "ZSaCyRAAAIFcr2qG",
    "name": "Bordeaux",
    "uid": "bordeaux",
    "keywords": "France Europe",
    "lat": 44.837789,
    "lng": -0.57918,
    "bounds": {
      "latitudeStart": 44.810741,
      "longitudeStart": -0.638699,
      "latitudeEnd": 44.916694,
      "longitudeEnd": -0.533325
    }
  },
  {
    "id": "ZSaCRRAAAKFcr2fw",
    "name": "Brighton",
    "uid": "brighton",
    "keywords": "UK England United Kingdom",
    "lat": 50.82294,
    "lng": -0.136267,
    "bounds": {
      "latitudeStart": 50.801252,
      "longitudeStart": -0.176119,
      "latitudeEnd": 50.873584,
      "longitudeEnd": -0.03626
    }
  },
  {
    "id": "ZSaB9BAAACVdr2Ze",
    "name": "Brisbane",
    "uid": "brisbane",
    "keywords": "Australia QLD Queensland",
    "lat": -27.470453,
    "lng": 153.026034,
    "region": {
      "latitude": -27.470453,
      "longitude": 153.026034,
      "latitudeDelta": 0.05,
      "longitudeDelta": 0.05
    },
    "bounds": {
      "latitudeStart": -27.767441,
      "longitudeStart": 152.668523,
      "latitudeEnd": -26.996845,
      "longitudeEnd": 153.31787
    },
    "trending": true
  },
  {
    "id": "ZXu8PhAAACAADEEh",
    "name": "Byron Bay",
    "uid": "byron-bay",
    "keywords": "Australia NSW New South Wales",
    "lat": -28.641912,
    "lng": 153.610517,
    "bounds": {
      "latitudeStart": -28.679357,
      "longitudeStart": 153.566967,
      "latitudeEnd": -28.61438,
      "longitudeEnd": 153.638832
    }
  },
  {
    "id": "ZSaBgBAAACBdr2Qq",
    "name": "Canberra",
    "uid": "canberra",
    "keywords": "Australia ACT Australian Capital Territory",
    "lat": -35.280185,
    "lng": 149.131032,
    "bounds": {
      "latitudeStart": -35.48026,
      "longitudeStart": 148.995922,
      "latitudeEnd": -35.147699,
      "longitudeEnd": 149.263643
    }
  },
  {
    "id": "ZSaBNhAAAIFcr2LD",
    "name": "Cape Town",
    "uid": "cape-town",
    "keywords": "South Africa",
    "lat": -33.924868,
    "lng": 18.424055,
    "region": {
      "latitude": -33.911798,
      "longitude": 18.422698,
      "latitudeDelta": 0.05,
      "longitudeDelta": 0.05
    },
    "bounds": {
      "latitudeStart": -34.359806,
      "longitudeStart": 18.307449,
      "latitudeEnd": -33.47127,
      "longitudeEnd": 19.00467
    },
    "trending": true
  },
  {
    "id": "ZSaAthAAAIVcr2BZ",
    "name": "Castlemaine",
    "uid": "castlemaine",
    "keywords": "Australia VIC Victoria",
    "lat": -37.058136,
    "lng": 144.218501,
    "bounds": {
      "latitudeStart": -37.106867,
      "longitudeStart": 144.167985,
      "latitudeEnd": -37.034882,
      "longitudeEnd": 144.271028
    }
  },
  {
    "id": "ZSZ_5RAAAM1cr1y6",
    "name": "Chennai",
    "uid": "chennai",
    "keywords": "India Asia",
    "lat": 13.08268,
    "lng": 80.270718,
    "bounds": {
      "latitudeStart": 12.699852,
      "longitudeStart": 79.968435,
      "latitudeEnd": 13.261166,
      "longitudeEnd": 80.336323
    }
  },
  {
    "id": "ZSZ_lBAAAO9cr1sr",
    "name": "Chiang Mai",
    "uid": "chiang-mai",
    "keywords": "Thailand Asia",
    "lat": 18.796464,
    "lng": 98.660059,
    "bounds": {
      "latitudeStart": 17.242275,
      "longitudeStart": 98.008039,
      "latitudeEnd": 20.14758,
      "longitudeEnd": 99.572913
    }
  },
  {
    "id": "ZSZ-5RAAAKFcr1hG",
    "name": "Chicago",
    "uid": "chicago",
    "keywords": "America United States USA Illinois",
    "lat": 41.878114,
    "lng": -87.629798,
    "bounds": {
      "latitudeStart": 41.644335,
      "longitudeStart": -87.940267,
      "latitudeEnd": 42.023131,
      "longitudeEnd": -87.523661
    }
  },
  {
    "id": "ZSZzXhAAAO9crx8P",
    "name": "Copenhagen",
    "uid": "copenhagen",
    "keywords": "Denmark Europe",
    "lat": 55.676097,
    "lng": 12.568337,
    "region": {
      "latitude": 55.676097,
      "longitude": 12.568337,
      "latitudeDelta": 0.05,
      "longitudeDelta": 0.05
    },
    "bounds": {
      "latitudeStart": 55.615441,
      "longitudeStart": 12.453382,
      "latitudeEnd": 55.727094,
      "longitudeEnd": 12.734265
    },
    "trending": true
  },
  {
    "id": "ZSZy6BAAAO9crxzD",
    "name": "Dakar",
    "uid": "dakar",
    "keywords": "Senegal Africa",
    "lat": 14.716677,
    "lng": -17.467686,
    "bounds": {
      "latitudeStart": 14.641935,
      "longitudeStart": -17.536581,
      "latitudeEnd": 14.780114,
      "longitudeEnd": -17.395069
    }
  },
  {
    "id": "ZSYdVBAAAKZWrYZZ",
    "name": "Detroit",
    "uid": "detroit",
    "keywords": "America United States USA Michigan",
    "lat": 42.331427,
    "lng": -83.045754,
    "bounds": {
      "latitudeStart": 42.255192,
      "longitudeStart": -83.287959,
      "latitudeEnd": 42.45023,
      "longitudeEnd": -82.910451
    }
  },
  {
    "id": "ZSZyUBAAAM1crxn3",
    "name": "Dubai",
    "uid": "dubai",
    "keywords": "United Arab Emirates UAE Middle East",
    "lat": 25.204849,
    "lng": 55.270783,
    "bounds": {
      "latitudeStart": 24.793484,
      "longitudeStart": 54.890454,
      "latitudeEnd": 25.358561,
      "longitudeEnd": 55.564522
    }
  },
  {
    "id": "ZSZyDxAAACVdrxim",
    "name": "Dublin",
    "uid": "dublin",
    "keywords": "Ireland UK United Kingdom",
    "lat": 53.349805,
    "lng": -6.26031,
    "region": {
      "latitude": 53.349805,
      "longitude": -6.26031,
      "latitudeDelta": 0.05,
      "longitudeDelta": 0.05
    },
    "bounds": {
      "latitudeStart": 53.22343,
      "longitudeStart": -6.447485,
      "latitudeEnd": 53.42521,
      "longitudeEnd": -6.043923
    },
    "trending": true
  },
  {
    "id": "ZSZxoBAAAKFcrxaA",
    "name": "Durban",
    "uid": "durban",
    "keywords": "South Africa",
    "lat": -29.85868,
    "lng": 31.02184,
    "bounds": {
      "latitudeStart": -29.95704,
      "longitudeStart": 30.921808,
      "latitudeEnd": -29.779907,
      "longitudeEnd": 31.060096
    }
  },
  {
    "id": "ZSZwXBAAAO9crxBL",
    "name": "Eastbourne",
    "uid": "eastbourne",
    "keywords": "UK United Kingdom England Britain",
    "lat": 50.768035,
    "lng": 0.290472,
    "bounds": {
      "latitudeStart": 50.748668,
      "longitudeStart": 0.235079,
      "latitudeEnd": 50.815833,
      "longitudeEnd": 0.341555
    }
  },
  {
    "id": "ZSZwPhAAAKFcrw-5",
    "name": "Encinitas",
    "uid": "encinitas",
    "keywords": "America United States USA California",
    "lat": 33.036987,
    "lng": -117.291982,
    "bounds": {
      "latitudeStart": 32.999272,
      "longitudeStart": -117.312903,
      "latitudeEnd": 33.088808,
      "longitudeEnd": -117.195566
    }
  },
  {
    "id": "ZSZvsRAAAIVcrwzR",
    "name": "Florence",
    "uid": "florence",
    "keywords": "Italy Europe",
    "lat": 43.767918,
    "lng": 11.252379,
    "bounds": {
      "latitudeStart": 43.72698,
      "longitudeStart": 11.154037,
      "latitudeEnd": 43.832937,
      "longitudeEnd": 11.327899
    }
  },
  {
    "id": "ZSZukBAAAO9crwdI",
    "name": "Ghent",
    "uid": "ghent",
    "keywords": "Belgium Europe",
    "lat": 51.050018,
    "lng": 3.730335,
    "bounds": {
      "latitudeStart": 50.979539,
      "longitudeStart": 3.579782,
      "latitudeEnd": 51.188892,
      "longitudeEnd": 3.849342
    }
  },
  {
    "id": "ZSZuOhAAAM1crwWe",
    "name": "Glasgow",
    "uid": "glasgow",
    "keywords": "UK United Kingdom England Britain",
    "lat": 55.86167,
    "lng": -4.258334,
    "bounds": {
      "latitudeStart": 55.781279,
      "longitudeStart": -4.3932,
      "latitudeEnd": 55.929641,
      "longitudeEnd": -4.071717
    }
  },
  {
    "id": "ZSZt5hAAAIVcrwPq",
    "name": "Goa",
    "uid": "goa",
    "keywords": "India Asia",
    "lat": 15.299327,
    "lng": 74.123996,
    "bounds": {
      "latitudeStart": 14.89844,
      "longitudeStart": 73.676952,
      "latitudeEnd": 15.801017,
      "longitudeEnd": 74.336437
    }
  },
  {
    "id": "ZSZtdRAAAO9crwF-",
    "name": "Gold Coast",
    "uid": "gold-coast",
    "keywords": "Australia QLD Queensland",
    "lat": -28.016667,
    "lng": 153.4,
    "bounds": {
      "latitudeStart": -28.200317,
      "longitudeStart": 153.186552,
      "latitudeEnd": -27.708126,
      "longitudeEnd": 153.552171
    }
  },
  {
    "id": "ZSZs1RAAAIFcrv5h",
    "name": "Hanoi",
    "uid": "hanoi",
    "keywords": "Vietnam Asia",
    "lat": 21.027764,
    "lng": 105.83416,
    "bounds": {
      "latitudeStart": 20.995099,
      "longitudeStart": 105.797482,
      "latitudeEnd": 21.05038,
      "longitudeEnd": 105.876446
    }
  },
  {
    "id": "ZXqTZRAAACcAbFM7",
    "name": "Havana",
    "uid": "havana",
    "keywords": "Cuba Caribbean",
    "lat": 23.113593,
    "lng": -82.366596,
    "bounds": {
      "latitudeStart": 22.920057,
      "longitudeStart": -82.574873,
      "latitudeEnd": 23.181316,
      "longitudeEnd": -82.091131
    }
  },
  {
    "id": "ZSZnpBAAADNdruSX",
    "name": "Hawaii",
    "uid": "hawaii",
    "keywords": "America United States USA Oahu Waikiki",
    "lat": 21.438912,
    "lng": -158.000056,
    "bounds": {
      "latitudeStart": 18.55,
      "longitudeStart": -160.53,
      "latitudeEnd": 22.37,
      "longitudeEnd": -154.48
    }
  },
  {
    "id": "ZSZnVhAAAIFcruME",
    "name": "Ho Chi Minh City",
    "uid": "ho-chi-minh-city",
    "keywords": "Vietnam Asia",
    "lat": 10.823099,
    "lng": 106.629664,
    "bounds": {
      "latitudeStart": 10.34937,
      "longitudeStart": 106.363878,
      "latitudeEnd": 11.160214,
      "longitudeEnd": 107.026577
    }
  },
  {
    "id": "ZSZm1BAAAM1cruCL",
    "name": "Hobart",
    "uid": "hobart",
    "keywords": "Australia Tasmania",
    "lat": -42.882605,
    "lng": 147.32572,
    "region": {
      "latitude": -42.882605,
      "longitude": 147.32572,
      "latitudeDelta": 0.05,
      "longitudeDelta": 0.05
    },
    "bounds": {
      "latitudeStart": -43.014123,
      "longitudeStart": 147.13366,
      "latitudeEnd": -42.655376,
      "longitudeEnd": 147.613383
    },
    "trending": true
  },
  {
    "id": "ZSZmZRAAAIVcrt4u",
    "name": "Hong Kong",
    "uid": "hong-kong",
    "keywords": "China Asia",
    "lat": 22.319304,
    "lng": 114.169361,
    "bounds": {
      "latitudeStart": 22.1435,
      "longitudeStart": 113.8259,
      "latitudeEnd": 22.561949,
      "longitudeEnd": 114.4529
    },
    "trending": true
  },
  {
    "id": "ZSZmExAAAO9crtyf",
    "name": "Hossegor",
    "uid": "hossegor",
    "keywords": "France Europe",
    "lat": 43.664619,
    "lng": -1.397687,
    "bounds": {
      "latitudeStart": 43.652244,
      "longitudeStart": -1.44625,
      "latitudeEnd": 43.683638,
      "longitudeEnd": -1.370558
    }
  },
  {
    "id": "ZXk4EhAAACkAZhWb",
    "name": "Ibiza",
    "uid": "ibiza",
    "keywords": "Spain Europe",
    "lat": 38.906734,
    "lng": 1.420598,
    "bounds": {
      "latitudeStart": 38.830416,
      "longitudeStart": 1.213264,
      "latitudeEnd": 39.11827,
      "longitudeEnd": 1.621512
    }
  },
  {
    "id": "ZSY9sxAAAPdZrhoR",
    "name": "Istanbul",
    "uid": "istanbul",
    "keywords": "Turkey Middle East",
    "lat": 41.008238,
    "lng": 28.978359,
    "bounds": {
      "latitudeStart": 40.811404,
      "longitudeStart": 28.595554,
      "latitudeEnd": 41.199239,
      "longitudeEnd": 29.428805
    }
  },
  {
    "id": "ZSY9YBAAAKlZrhiQ",
    "name": "Jakarta",
    "uid": "jakarta",
    "keywords": "Indonesia Asia",
    "lat": -6.194449,
    "lng": 106.82292,
    "bounds": {
      "latitudeStart": -6.370833,
      "longitudeStart": 106.686211,
      "latitudeEnd": -6.08866,
      "longitudeEnd": 106.972825
    }
  },
  {
    "id": "ZSY9KRAAAFRZrheR",
    "name": "Jeffreys Bay",
    "uid": "jeffreys-bay",
    "keywords": "South Africa",
    "lat": -34.050671,
    "lng": 24.910154,
    "bounds": {
      "latitudeStart": -34.117749,
      "longitudeStart": 24.86978,
      "latitudeEnd": -33.996319,
      "longitudeEnd": 24.935501
    }
  },
  {
    "id": "ZSY82xAAAI9ZrhYb",
    "name": "Jericoacoara",
    "uid": "jericoacoara",
    "keywords": "Brazil South America",
    "lat": -2.797388,
    "lng": -40.512403,
    "bounds": {
      "latitudeStart": -2.802638,
      "longitudeStart": -40.520594,
      "latitudeEnd": -2.788885,
      "longitudeEnd": -40.503744
    }
  },
  {
    "id": "ZSY8lBAAAE5arhTR",
    "name": "Johannesburg",
    "uid": "johannesburg",
    "keywords": "South Africa",
    "lat": -26.204103,
    "lng": 28.047305,
    "region": {
      "latitude": -26.164872,
      "longitude": 28.062518,
      "latitudeDelta": 0.2,
      "longitudeDelta": 0.2
    },
    "bounds": {
      "latitudeStart": -26.238923,
      "longitudeStart": 27.942449,
      "latitudeEnd": -26.10412,
      "longitudeEnd": 28.1376
    },
    "trending": true
  },
  {
    "id": "ZSY8WhAAAFRZrhPI",
    "name": "Kathmandu",
    "uid": "kathmandu",
    "keywords": "Nepal Asia",
    "lat": 27.717245,
    "lng": 85.323961,
    "bounds": {
      "latitudeStart": 27.667984,
      "longitudeStart": 85.279098,
      "latitudeEnd": 27.749937,
      "longitudeEnd": 85.373168
    }
  },
  {
    "id": "ZSY8CRAAAIlZrhJD",
    "name": "Kuala Lumpur",
    "uid": "kuala-lumpur",
    "keywords": "Malaysia Asia",
    "lat": 3.13192,
    "lng": 101.684059,
    "bounds": {
      "latitudeStart": 3.033633,
      "longitudeStart": 101.61545,
      "latitudeEnd": 3.243379,
      "longitudeEnd": 101.758529
    }
  },
  {
    "id": "ZYUvoRIAAH-D_Fqj",
    "name": "Kuching",
    "uid": "kuching",
    "keywords": "Malaysia Asia",
    "lat": 1.553379,
    "lng": 110.359503,
    "bounds": {
      "latitudeStart": 1.431599,
      "longitudeStart": 110.126061,
      "latitudeEnd": 1.804763,
      "longitudeEnd": 110.526076
    }
  },
  {
    "id": "ZSY75hAAAIlZrhGo",
    "name": "Lagos",
    "uid": "lagos",
    "keywords": "Nigeria Africa",
    "lat": 6.524379,
    "lng": 3.379206,
    "region": {
      "latitude": 6.454879,
      "longitude": 3.424598,
      "latitudeDelta": 0.5,
      "longitudeDelta": 0.5
    },
    "bounds": {
      "latitudeStart": 6.393351,
      "longitudeStart": 3.098273,
      "latitudeEnd": 6.702759,
      "longitudeEnd": 3.564808
    },
    "trending": true
  },
  {
    "id": "ZSYiuRAAAPhWrZ63",
    "name": "Lake District",
    "uid": "the-lake-district",
    "keywords": "UK United Kingdom England Britain",
    "lat": 54.46087,
    "lng": -3.088625,
    "bounds": {
      "latitudeStart": 54.235746,
      "longitudeStart": -3.414869,
      "latitudeEnd": 54.717123,
      "longitudeEnd": -2.756446
    }
  },
  {
    "id": "ZSY7qxAAAI9ZrhCY",
    "name": "Le Marche",
    "uid": "le-marche",
    "keywords": "Italy Europe",
    "lat": 43.462735,
    "lng": 13.358729,
    "bounds": {
      "latitudeStart": 42.687156,
      "longitudeStart": 12.185454,
      "latitudeEnd": 43.969564,
      "longitudeEnd": 13.916725
    }
  },
  {
    "id": "ZSY7OBAAAIlZrg6Q",
    "name": "Lisbon",
    "uid": "lisbon",
    "keywords": "Portugal Europe",
    "lat": 38.722252,
    "lng": -9.139337,
    "bounds": {
      "latitudeStart": 38.691399,
      "longitudeStart": -9.229836,
      "latitudeEnd": 38.79676,
      "longitudeEnd": -9.089636
    }
  },
  {
    "id": "ZSY6GBAAADFarglw",
    "name": "Madison",
    "uid": "madison",
    "keywords": "America United States USA Wisconsin",
    "lat": 43.072166,
    "lng": -89.40075,
    "bounds": {
      "latitudeStart": 42.998071,
      "longitudeStart": -89.566389,
      "latitudeEnd": 43.171916,
      "longitudeEnd": -89.246795
    }
  },
  {
    "id": "ZSY50xAAAKlZrggz",
    "name": "Madrid",
    "uid": "madrid",
    "keywords": "Spain Europe",
    "lat": 40.416775,
    "lng": -3.70379,
    "bounds": {
      "latitudeStart": 40.312064,
      "longitudeStart": -3.834162,
      "latitudeEnd": 40.563845,
      "longitudeEnd": -3.524911
    }
  },
  {
    "id": "ZSY5mBAAAPdZrgcc",
    "name": "Manchester",
    "uid": "manchester",
    "keywords": "UK United Kingdom England Britain",
    "lat": 53.480759,
    "lng": -2.24263,
    "bounds": {
      "latitudeStart": 53.399903,
      "longitudeStart": -2.300097,
      "latitudeEnd": 53.544588,
      "longitudeEnd": -2.146829
    }
  },
  {
    "id": "ZSYXwxAAAEZWrW0g",
    "name": "Marbella",
    "uid": "marbella",
    "keywords": "Spain Europe",
    "lat": 36.510283,
    "lng": -4.885258,
    "bounds": {
      "latitudeStart": 36.469255,
      "longitudeStart": -4.997958,
      "latitudeEnd": 36.532446,
      "longitudeEnd": -4.732042
    }
  },
  {
    "id": "ZSY5PhAAAI9ZrgWH",
    "name": "Margate",
    "uid": "margate",
    "keywords": "UK United Kingdom England Britain",
    "lat": 51.389646,
    "lng": 1.386834,
    "bounds": {
      "latitudeStart": 51.360872,
      "longitudeStart": 1.342371,
      "latitudeEnd": 51.393624,
      "longitudeEnd": 1.423782
    }
  },
  {
    "id": "ZSY45BAAAG1argPU",
    "name": "Marrakesh",
    "uid": "marrakesh",
    "keywords": "Morocco Africa",
    "lat": 31.622522,
    "lng": -7.989826,
    "bounds": {
      "latitudeStart": 31.552976,
      "longitudeStart": -8.12808,
      "latitudeEnd": 31.716267,
      "longitudeEnd": -7.887626
    }
  },
  {
    "id": "ZSY4fxAAAKlZrgH6",
    "name": "Marseille",
    "uid": "marseille",
    "keywords": "France Europe",
    "lat": 43.296482,
    "lng": 5.36978,
    "bounds": {
      "latitudeStart": 43.169634,
      "longitudeStart": 5.228753,
      "latitudeEnd": 43.391057,
      "longitudeEnd": 5.532543
    }
  },
  {
    "id": "ZSY4ERAAAE5arf_q",
    "name": "Mexico City",
    "uid": "mexico-city",
    "keywords": "Mexico North America",
    "lat": 19.432608,
    "lng": -99.133208,
    "bounds": {
      "latitudeStart": 19.18871,
      "longitudeStart": -99.326777,
      "latitudeEnd": 19.592757,
      "longitudeEnd": -98.960448
    }
  },
  {
    "id": "ZSYYoBAAAKZWrXEX",
    "name": "Milan",
    "uid": "milan",
    "keywords": "Italy Europe",
    "lat": 45.464204,
    "lng": 9.189982,
    "bounds": {
      "latitudeStart": 45.389779,
      "longitudeStart": 9.065118,
      "latitudeEnd": 45.535689,
      "longitudeEnd": 9.290346
    }
  },
  {
    "id": "ZXqPixAAACgAbEHp",
    "name": "Minnesota",
    "uid": "minnesota",
    "keywords": "America United States USA",
    "lat": 46.729553,
    "lng": -94.6859,
    "bounds": {
      "latitudeStart": 43.499361,
      "longitudeStart": -97.239093,
      "latitudeEnd": 49.384472,
      "longitudeEnd": -89.483812
    }
  },
  {
    "id": "ZSY3rRAAAKlZrf4m",
    "name": "Mojave Desert",
    "uid": "mojave-desert",
    "keywords": "America United States USA California",
    "lat": 35.010991,
    "lng": -115.473355,
    "bounds": {
      "latitudeStart": 32.528832,
      "longitudeStart": -121.438176,
      "latitudeEnd": 35.809236,
      "longitudeEnd": -114.131211
    }
  },
  {
    "id": "ZSY3bRAAAAtarf0J",
    "name": "Montreal",
    "uid": "montreal",
    "keywords": "Canada North America",
    "lat": 45.501887,
    "lng": -73.567392,
    "bounds": {
      "latitudeStart": 45.414588,
      "longitudeStart": -73.947543,
      "latitudeEnd": 45.703778,
      "longitudeEnd": -73.476204
    }
  },
  {
    "id": "ZSY20RAAAIlZrfo6",
    "name": "Mumbai",
    "uid": "mumbai",
    "keywords": "India Asia",
    "lat": 19.075984,
    "lng": 72.877656,
    "bounds": {
      "latitudeStart": 18.892868,
      "longitudeStart": 72.775873,
      "latitudeEnd": 19.271634,
      "longitudeEnd": 72.986499
    }
  },
  {
    "id": "ZSY65xAAAE5arg0c",
    "name": "London",
    "uid": "london",
    "keywords": "UK United Kingdom England Britain",
    "lat": 51.507218,
    "lng": -0.127586,
    "region": {
      "latitude": 51.52649,
      "longitude": -0.107875,
      "latitudeDelta": 0.05,
      "longitudeDelta": 0.05
    },
    "bounds": {
      "latitudeStart": 51.38494,
      "longitudeStart": -0.351468,
      "latitudeEnd": 51.672343,
      "longitudeEnd": 0.148271
    },
    "trending": true
  },
  {
    "id": "ZSY6khAAAFRZrgub",
    "name": "Los Angeles",
    "uid": "los-angeles",
    "keywords": "America United States USA California",
    "lat": 34.054908,
    "lng": -118.242643,
    "region": {
      "latitude": 34.054908,
      "longitude": -118.242643,
      "latitudeDelta": 0.05,
      "longitudeDelta": 0.05
    },
    "bounds": {
      "latitudeStart": 33.703652,
      "longitudeStart": -118.668176,
      "latitudeEnd": 34.337306,
      "longitudeEnd": -118.155289
    },
    "trending": true
  },
  {
    "id": "ZSY4VxAAAAtargFC",
    "name": "Melbourne",
    "uid": "melbourne",
    "keywords": "Australia VIC Victoria",
    "lat": -37.813628,
    "lng": 144.963058,
    "region": {
      "latitude": -37.813628,
      "longitude": 144.963058,
      "latitudeDelta": 0.05,
      "longitudeDelta": 0.05
    },
    "bounds": {
      "latitudeStart": -38.433859,
      "longitudeStart": 144.593742,
      "latitudeEnd": -37.511274,
      "longitudeEnd": 145.512529
    },
    "trending": true
  },
  {
    "id": "ZSXp2RAAAG9QrJvl",
    "name": "New York",
    "uid": "new-york",
    "keywords": "America United States USA",
    "lat": 40.712775,
    "lng": -74.005973,
    "region": {
      "latitude": 40.725257,
      "longitude": -73.990349,
      "latitudeDelta": 0.05,
      "longitudeDelta": 0.05
    },
    "bounds": {
      "latitudeStart": 40.477399,
      "longitudeStart": -74.25909,
      "latitudeEnd": 40.917577,
      "longitudeEnd": -73.700272
    },
    "trending": true
  },
  {
    "id": "ZP6qOxIAACIAkMGl",
    "name": "Sydney",
    "uid": "sydney",
    "keywords": "Australia NSW New South Wales",
    "lat": -33.86882,
    "lng": 151.209296,
    "region": {
      "latitude": -33.86882,
      "longitude": 151.209296,
      "latitudeDelta": 0.03,
      "longitudeDelta": 0.03
    },
    "bounds": {
      "latitudeStart": -34.118347,
      "longitudeStart": 150.520929,
      "latitudeEnd": -33.578141,
      "longitudeEnd": 151.343021
    },
    "trending": true
  },
  {
    "id": "ZSYiQxAAAMdXrZyc",
    "name": "Tokyo",
    "uid": "tokyo",
    "keywords": "Japan Asia",
    "lat": 35.676423,
    "lng": 139.650027,
    "region": {
      "latitude": 35.661971,
      "longitude": 139.703795,
      "latitudeDelta": 0.05,
      "longitudeDelta": 0.05
    },
    "bounds": {
      "latitudeStart": 34.577633,
      "longitudeStart": 138.29911,
      "latitudeEnd": 36.440848,
      "longitudeEnd": 141.240514
    },
    "trending": true
  }
]
